philip_pal2/__init__.py
philip_pal2/__main__.py
philip_pal2/philip_cli.py
philip_pal2/philip_if.py
philip_pal2/mem_map/mm_PHiLIP_philip_map_2_0_0.csv
philip_pal2/mem_map/mm_PHiLIP_philip_map_2_0_1.csv
philip_pal2/mem_map/mm_PHiLIP_philip_map_5ea942551b11de32981e5fe84c0ad1b2.csv
philip_pal2/mem_map/mm_PHiLIP_philip_map_aa9f3eb5aa01fd55e4fc3badb08d6468.csv
philip_pal2/mem_map/mm_PHiLIP_philip_map_compressed_2_0_0.csv
philip_pal2/mem_map/mm_PHiLIP_philip_map_compressed_2_0_1.csv
philip_pal2-0.0.2.dist-info/LICENSE.txt
philip_pal2-0.0.2.dist-info/METADATA
philip_pal2-0.0.2.dist-info/WHEEL
philip_pal2-0.0.2.dist-info/entry_points.txt
philip_pal2-0.0.2.dist-info/top_level.txt
philip_pal2-0.0.2.dist-info/RECORD
